odoo/addons/stock_picking_group_by_base/README.rst
odoo/addons/stock_picking_group_by_base/__init__.py
odoo/addons/stock_picking_group_by_base/__manifest__.py
odoo/addons/stock_picking_group_by_base/hooks.py
odoo/addons/stock_picking_group_by_base/i18n/it.po
odoo/addons/stock_picking_group_by_base/i18n/pt.po
odoo/addons/stock_picking_group_by_base/i18n/pt_BR.po
odoo/addons/stock_picking_group_by_base/i18n/stock_picking_group_by_base.pot
odoo/addons/stock_picking_group_by_base/models/__init__.py
odoo/addons/stock_picking_group_by_base/models/stock_picking.py
odoo/addons/stock_picking_group_by_base/readme/CONTRIBUTORS.md
odoo/addons/stock_picking_group_by_base/readme/DESCRIPTION.md
odoo/addons/stock_picking_group_by_base/readme/USAGE.md
odoo/addons/stock_picking_group_by_base/static/description/icon.png
odoo/addons/stock_picking_group_by_base/static/description/index.html
odoo/addons/stock_picking_group_by_base/tests/__init__.py
odoo/addons/stock_picking_group_by_base/tests/test_groupby_index.py
odoo_addon_stock_picking_group_by_base-18.0.1.0.0.6.dist-info/METADATA
odoo_addon_stock_picking_group_by_base-18.0.1.0.0.6.dist-info/WHEEL
odoo_addon_stock_picking_group_by_base-18.0.1.0.0.6.dist-info/top_level.txt
odoo_addon_stock_picking_group_by_base-18.0.1.0.0.6.dist-info/RECORD
